{
  "updated_at": "2026-07-16T23:56:32+08:00",
  "updated_at_display": "2026-07-16 23:56:32",
  "target_sbi": 1,
  "windows": {
    "1h": {
      "stations": [],
      "sample_count": 1,
      "note": "樣本數不足，無法判斷"
    },
    "2h": {
      "stations": [
        {
          "sno": "NTPC-500203114",
          "sna": "光復中興北街175巷口(西北側)",
          "sarea": "三重區",
          "city": "新北市",
          "sbi": 1,
          "bemp": 39,
          "tot": 41,
          "last_mday": "20260716T221004",
          "sample_count": 2
        },
        {
          "sno": "NTPC-500209027",
          "sna": "五工二五工一路口(泰博科技)",
          "sarea": "五股區",
          "city": "新北市",
          "sbi": 1,
          "bemp": 19,
          "tot": 20,
          "last_mday": "20260716T220404",
          "sample_count": 2
        },
        {
          "sno": "NTPC-500227061",
          "sna": "直潭淨水廠(直潭二街)",
          "sarea": "新店區",
          "city": "新北市",
          "sbi": 1,
          "bemp": 14,
          "tot": 15,
          "last_mday": "20260716T162502",
          "sample_count": 2
        },
        {
          "sno": "NTPC-500218143",
          "sna": "文丘公園",
          "sarea": "板橋區",
          "city": "新北市",
          "sbi": 1,
          "bemp": 13,
          "tot": 15,
          "last_mday": "20260716T220603",
          "sample_count": 2
        },
        {
          "sno": "NTPC-500218184",
          "sna": "華江橋自行車牽引道",
          "sarea": "板橋區",
          "city": "新北市",
          "sbi": 1,
          "bemp": 15,
          "tot": 16,
          "last_mday": "20260716T221902",
          "sample_count": 2
        },
        {
          "sno": "NTPC-500216065",
          "sna": "師大林口校區行政大樓",
          "sarea": "林口區",
          "city": "新北市",
          "sbi": 1,
          "bemp": 17,
          "tot": 18,
          "last_mday": "20260716T205003",
          "sample_count": 2
        },
        {
          "sno": "NTPC-500231067",
          "sna": "東豐街85巷口",
          "sarea": "樹林區",
          "city": "新北市",
          "sbi": 1,
          "bemp": 11,
          "tot": 12,
          "last_mday": "20260716T221403",
          "sample_count": 2
        },
        {
          "sno": "NTPC-500223048",
          "sna": "輕軌竿蓁林站",
          "sarea": "淡水區",
          "city": "新北市",
          "sbi": 1,
          "bemp": 9,
          "tot": 10,
          "last_mday": "20260716T201902",
          "sample_count": 2
        }
      ],
      "sample_count": 2
    },
    "4h": {
      "stations": [
        {
          "sno": "NTPC-500227061",
          "sna": "直潭淨水廠(直潭二街)",
          "sarea": "新店區",
          "city": "新北市",
          "sbi": 1,
          "bemp": 14,
          "tot": 15,
          "last_mday": "20260716T162502",
          "sample_count": 3
        }
      ],
      "sample_count": 3
    }
  }
}